__init__.py
msc.py
twostageclustering-0.0.2.dist-info/LICENSE
twostageclustering-0.0.2.dist-info/METADATA
twostageclustering-0.0.2.dist-info/WHEEL
twostageclustering-0.0.2.dist-info/top_level.txt
twostageclustering-0.0.2.dist-info/RECORD
