Metadata-Version: 2.1
Name: twostageclustering
Version: 0.0.2
Summary: Multi Stage Clustering
Home-page: https://github.com/ramachaitanya0/MultiStageClustering
Author: Ishita Roy,  Rama Chaitanya Karanam
Author-email: ramachaitanya0@gmail.com
License: MIT
Platform: UNKNOWN
Classifier: Programming Language :: Python :: 3 
Classifier: License :: OSI Approved :: MIT License
Classifier: Operating System :: OS Independent
License-File: LICENSE
Requires-Dist: pandas (>=1.2.0)
Requires-Dist: numpy (>=1.20.1)
Requires-Dist: scikit-learn (>=1.0.2)
